memorybox/__init__.py
memorybox/client.py
memorybox/exceptions.py
memorybox/models.py
memorybox/resources.py
memorybox-1.0.0.dist-info/licenses/LICENSE
memorybox-1.0.0.dist-info/METADATA
memorybox-1.0.0.dist-info/WHEEL
memorybox-1.0.0.dist-info/top_level.txt
memorybox-1.0.0.dist-info/RECORD
