Metadata-Version: 2.4
Name: memorybox
Version: 1.0.0
Summary: Official Python SDK for Memory Box - Universal AI Memory Management
Author-email: Memory Box Team <support@hawltechs.com>
License-Expression: MIT
Project-URL: Homepage, https://memorybox.hawltechs.com
Project-URL: Documentation, https://memorybox.hawltechs.com/docs
Project-URL: Repository, https://github.com/ChonghaoSu/Memory-Box-Website
Project-URL: Issues, https://github.com/ChonghaoSu/Memory-Box-Website/issues
Keywords: memorybox,ai,memory,llm,chatgpt,claude,api,sdk
Classifier: Development Status :: 4 - Beta
Classifier: Intended Audience :: Developers
Classifier: Operating System :: OS Independent
Classifier: Programming Language :: Python :: 3
Classifier: Programming Language :: Python :: 3.8
Classifier: Programming Language :: Python :: 3.9
Classifier: Programming Language :: Python :: 3.10
Classifier: Programming Language :: Python :: 3.11
Classifier: Programming Language :: Python :: 3.12
Classifier: Topic :: Software Development :: Libraries :: Python Modules
Classifier: Topic :: Scientific/Engineering :: Artificial Intelligence
Requires-Python: >=3.8
License-File: LICENSE
Requires-Dist: requests>=2.25.0
Provides-Extra: dev
Requires-Dist: pytest>=6.0; extra == "dev"
Requires-Dist: pytest-cov>=2.0; extra == "dev"
Requires-Dist: black>=21.0; extra == "dev"
Requires-Dist: isort>=5.0; extra == "dev"
Requires-Dist: mypy>=0.900; extra == "dev"
Requires-Dist: responses>=0.20.0; extra == "dev"
Dynamic: license-file
